feedgen/compat.py
feedgen/__init__.py
feedgen/util.py
feedgen/feed.py
feedgen/version.py
feedgen/entry.py
feedgen/__main__.py
feedgen/ext/dc.py
feedgen/ext/__init__.py
feedgen/ext/base.py
feedgen/ext/podcast_entry.py
feedgen/ext/syndication.py
feedgen/ext/torrent.py
feedgen/ext/podcast.py
feedgen-0.4.0.dist-info/top_level.txt
feedgen-0.4.0.dist-info/METADATA
feedgen-0.4.0.dist-info/DESCRIPTION.rst
feedgen-0.4.0.dist-info/metadata.json
feedgen-0.4.0.dist-info/WHEEL
feedgen-0.4.0.dist-info/RECORD
