Metadata-Version: 2.0
Name: feedgen
Version: 0.4.0
Summary: Feed Generator (ATOM, RSS, Podcasts)
Home-page: http://lkiesow.github.io/python-feedgen
Author: Lars Kiesow
Author-email: lkiesow@uos.de
License: FreeBSD and LGPLv3+
Keywords: feed,ATOM,RSS,podcast
Platform: UNKNOWN
Classifier: Development Status :: 5 - Production/Stable
Classifier: Intended Audience :: Developers
Classifier: Intended Audience :: Information Technology
Classifier: Intended Audience :: Science/Research
Classifier: License :: OSI Approved :: BSD License
Classifier: License :: OSI Approved :: GNU Lesser General Public License v3 or later (LGPLv3+)
Classifier: Natural Language :: English
Classifier: Operating System :: OS Independent
Classifier: Programming Language :: Python
Classifier: Programming Language :: Python :: 2
Classifier: Programming Language :: Python :: 3
Classifier: Topic :: Communications
Classifier: Topic :: Internet
Classifier: Topic :: Text Processing
Classifier: Topic :: Text Processing :: Markup
Classifier: Topic :: Text Processing :: Markup :: XML
Requires-Dist: lxml
Requires-Dist: python-dateutil
